{
    "$schema": "http://json-schema.org/draft-06/schema#",
    "$id": "urn:nuage-metroae:nsgv-bootstrap",
    "title": "NSGv Bootstrap",
    "description": "Specify zero-factor bootstrap configuration for NSGvs.",
    "type": "object",
    "widget": "form",
    "properties": {
        "vsd_license_file": {
            "type": "string",
            "title": "VSD License Filename",
            "default": "",
            "description": "Filename for the license file for the VSD.",
            "propertyOrder": 10
        },
        "nsgv_organization": {
            "type": "string",
            "title": "Organization for NSGvs",
            "default": "",
            "sectionBegin": "Organization",
            "description": "Organization name for NSGvs on the VSD.",
            "propertyOrder": 20
        },
        "nsgv_name": {
            "type": "string",
            "title": "Name of NSGv",
            "description": "Name of NSGvs on the VSD.",
            "default": "",
            "sectionEnd": "Organization",
            "propertyOrder": 30
        },
        "proxy_user_first_name": {
            "type": "string",
            "title": "Proxy User First Name",
            "description": "First name for proxy user. Password for proxy user is set in credentials.",
            "sectionBegin": "Proxy User",
            "default": "",
            "propertyOrder": 40
        },
        "proxy_user_last_name": {
            "type": "string",
            "title": "Proxy User Last Name",
            "description": "Last name for proxy user. Password for proxy user is set in credentials.",
            "default": "",
            "propertyOrder": 50
        },
        "proxy_user_email": {
            "type": "string",
            "title": "Proxy User Email",
            "description": "Email address for proxy user. Password for proxy user is set in credentials.",
            "sectionEnd": "Proxy User",
            "default": "",
            "propertyOrder": 60
        },
        "nsg_infrastructure_profile_name": {
            "type": "string",
            "title": "NSG Infrastructure Profile Name",
            "description": "Name for the infrastructure gateway profile on the VSD.",
            "sectionBegin": "NSG Infrastructure",
            "default": "",
            "propertyOrder": 70
        },
        "nsg_template_name": {
            "type": "string",
            "title": "NSGv Template Name",
            "description": "Name for the gateway template on the VSD.",
            "default": "",
            "propertyOrder": 80
        },
        "proxy_dns_name": {
            "type": "string",
            "title": "Proxy DNS Name",
            "description": "DNS name for the proxy.",
            "sectionEnd": "NSG Infrastructure",
            "default": "",
            "propertyOrder": 90
        },
        "vsc_infrastructure_profile_name": {
            "type": "string",
            "title": "VSC Infrastructure Profile Name",
            "description": "Name of the infrastructure VSC profile on the VSD.",
            "sectionBegin": "VSC Infrastructure",
            "default": "",
            "propertyOrder": 100
        },
        "first_controller_address": {
            "type": "string",
            "title": "Address of First VSC",
            "default": "",
            "description": "IP address of the first controller.",
            "format": "hostname",
            "propertyOrder": 110
        },
        "second_controller_address": {
            "type": "string",
            "title": "Address of Second VSC",
            "default": "",
            "description": "IP address of the second controller.",
            "sectionEnd": "VSC Infrastructure",
            "format": "hostname",
            "propertyOrder": 120
        },
        "nsg_network_port_name": {
            "type": "string",
            "title": "NSG Network Port Name",
            "description": "Name of the NSG network port.",
            "default": "",
            "sectionBegin": "NSG Ports",
            "propertyOrder": 130
        },
        "nsg_network_port_physical_name": {
            "type": "string",
            "title": "NSG Network Port Physical Name",
            "description": "Physical name of the NSG network port.",
            "default": "",
            "propertyOrder": 140
        },
        "nsg_access_port_name": {
            "type": "string",
            "title": "NSG Access Port Name",
            "description": "Name of the NSG access port.",
            "default": "",
            "propertyOrder": 150
        },
        "nsg_access_port_physical_name": {
            "type": "string",
            "title": "NSG Access Port Physical Name",
            "description": "Physical name of the NSG access port.",
            "default": "",
            "propertyOrder": 160
        },
        "nsg_access_port_vlan_range": {
            "type": "string",
            "title": "NSG Access Port VLAN Range",
            "description": "Range of VLANs on the NSG access port. i.e. 0-100",
            "default": "",
            "propertyOrder": 170
        },
        "nsg_access_port_vlan_value": {
            "type": "integer",
            "title": "NSG Access Port VLAN Value",
            "description": "Value of VLAN on the NSG access port.",
            "sectionEnd": "NSG Ports",
            "default": "",
            "propertyOrder": 180
        }
    }
}
